drf_mixin_tools/__init__.py
drf_mixin_tools/mixins.py
drf_mixin_tools/serializers.py
drf_mixin_tools-0.0.3.dist-info/LICENSE
drf_mixin_tools-0.0.3.dist-info/METADATA
drf_mixin_tools-0.0.3.dist-info/WHEEL
drf_mixin_tools-0.0.3.dist-info/top_level.txt
drf_mixin_tools-0.0.3.dist-info/RECORD
