Metadata-Version: 2.1
Name: drf-mixin-tools
Version: 0.0.3
Summary: Collection of helpfull tools for drf
Home-page: https://github.com/nabakirov/drf_mixin_tools
Author: Nursultan Abakirov
Author-email: nabakirov@gmail.com
License: MIT
Platform: UNKNOWN
Classifier: Development Status :: 2 - Pre-Alpha
Classifier: Environment :: Web Environment
Classifier: Framework :: Django
Classifier: Intended Audience :: Developers
Classifier: License :: OSI Approved :: MIT License
Classifier: Operating System :: OS Independent
Classifier: Natural Language :: English
Classifier: Programming Language :: Python :: 3
Classifier: Topic :: Internet :: WWW/HTTP
Requires-Dist: Django (>=2.0.4)
Requires-Dist: djangorestframework (>=3.8.2)
